README.rst
setup.cfg
setup.py
remote_runner/__init__.py
remote_runner/errors.py
remote_runner/pbs.py
remote_runner/postman.py
remote_runner/utility.py
remote_runner.egg-info/PKG-INFO
remote_runner.egg-info/SOURCES.txt
remote_runner.egg-info/dependency_links.txt
remote_runner.egg-info/requires.txt
remote_runner.egg-info/top_level.txt