Metadata-Version: 1.2
Name: remote-runner
Version: 0.1.1
Summary: Batch remote execution of python scripts
Home-page: https://github.com/sizmailov/remote-runner
Maintainer: Sergei Izmailov
Maintainer-email: sergei.a.izmailov@gmail.com
License: BSD
Platform: UNKNOWN
